Workbook
Name aporte: Planilha1!$F$23
Name qtd_anos: Planilha1!$F$24
Name rendimento_carteira: Planilha1!$D$17
Name salario: Planilha1!$D$16
Name sugestal_investimento: Planilha1!$D$18
Name taxa_mensal: Planilha1!$F$25

Sheet Planilha1
C15: CONFIGURAÇÕES
C16: Salário | D16: 2000
C17: Rendimento Carteira | D17: 0.006
A18: 30 | C18: Suguestao de Investimento | D18: =aporte -> 200
A19: 2
A21: 5
A22: 10 | B22: INVESTIMENTO MENSAL
A23: 20 | B23: Quanto investir pormês | F23: 200
A24: 30 | B24: Por quantos Anos | F24: 5
B25: Taxa de Redimento mensal | F25: 0.01079
B26: Patrimonio acumalado | F26: =FV(F25,F24*12,F23*-1) -> 16755.383
B27: Dividendo mensais | F27: =F26*D17 -> 100.5323
B29: CENARIOS | G29: Dividendo
B30: Quantos em 2 Anos | F30: =FV($F$25,A19*12,$F$23*-1) -> 5445.5255 | G30: =F30*D17 -> 32.673153
B31: Quantos em 5 Anos | F31: =FV($F$25,$A21*12,$F$23*-1) -> 16755.383 | G31: =F31*D17 -> 100.5323
B32: Quantos em 10 Anos | F32: =FV($F$25,$A22*12,$F$23*-1) -> 48656.843 | G32: =F32*D17 -> 291.94106
B33: Quantos em 20 Anos | F33: =FV($F$25,$A23*12,$F$23*-1) -> 225039.68 | G33: =F33*D17 -> 1350.2381
B34: Quantos em 30 Anos | F34: =FV($F$25,$A18*12,$F$23*-1) -> 864433.93 | G34: =F34*D17 -> 5186.6036
B37: PERFIL | F37: Agressivo
B38: VALOR A SER INVESTIDO POR MÊS | F38: =aporte -> 200
B40: TIPO DE FII | D40: PERCENTUAL | F40: VALORES
B41: PAPEL | D41: =VLOOKUP($F$37&"-"&$B41,Planilha2!$A:$D,4,FALSE) -> 0.5 | F41: =D41*$F$38 -> 100
B42: TIJOLO | D42: =VLOOKUP($F$37&"-"&$B42,Planilha2!$A:$D,4,FALSE) -> 0.1 | F42: =D42*$F$38 -> 20
B43: HIBRIDOS | D43: =VLOOKUP($F$37&"-"&$B43,Planilha2!$A:$D,4,FALSE) -> 0.05 | F43: =D43*$F$38 -> 10
B44: FOFS | D44: =VLOOKUP($F$37&"-"&$B44,Planilha2!$A:$D,4,FALSE) -> 0.05 | F44: =D44*$F$38 -> 10
B45: DESENVOLVIMENTO | D45: =VLOOKUP($F$37&"-"&$B45,Planilha2!$A:$D,4,FALSE) -> 0.2 | F45: =D45*$F$38 -> 40
B46: HOTELARIA | D46: =VLOOKUP($F$37&"-"&$B46,Planilha2!$A:$D,4,FALSE) -> 0.1 | F46: =D46*$F$38 -> 20
B47: =SUM(F41:F46) -> 200

Sheet Planilha2
A2: CHAVE | B2: PERFIL | C2: TIPO DE FII | D2: %
A3: Conservador-PAPEL | B3: Conservador | C3: PAPEL | D3: 0.3
A4: Conservador-TIJOLO | B4: Conservador | C4: TIJOLO | D4: 0.5
A5: Conservador-HIBRIDOS | B5: Conservador | C5: HIBRIDOS | D5: 0.1 | F5: Moderado-TIJOLO | H5: =VLOOKUP(F5,$A:$D,4,FALSE) -> 0.2
A6: Conservador-FOFS | B6: Conservador | C6: FOFS | D6: 0.1
A7: Conservador-DESENVOLVIMENTO | B7: Conservador | C7: DESENVOLVIMENTO | D7: 0
A8: Conservador-HOTELARIA | B8: Conservador | C8: HOTELARIA | D8: 0
A9: Moderado-PAPEL | B9: Moderado | C9: PAPEL | D9: 0.32
A10: Moderado-TIJOLO | B10: Moderado | C10: TIJOLO | D10: 0.2
A11: Moderado-HIBRIDOS | B11: Moderado | C11: HIBRIDOS | D11: 0.08
A12: Moderado-FOFS | B12: Moderado | C12: FOFS | D12: 0.1
A13: Moderado-DESENVOLVIMENTO | B13: Moderado | C13: DESENVOLVIMENTO | D13: 0.1
A14: Moderado-HOTELARIA | B14: Moderado | C14: HOTELARIA | D14: 0.1
A15: Agressivo-PAPEL | B15: Agressivo | C15: PAPEL | D15: 0.5
A16: Agressivo-TIJOLO | B16: Agressivo | C16: TIJOLO | D16: 0.1
A17: Agressivo-HIBRIDOS | B17: Agressivo | C17: HIBRIDOS | D17: 0.05
... A20: Agressivo-HOTELARIA | B20: Agressivo | C20: HOTELARIA | D20: 0.1
